{
  "id" : "5966e33c4e686b508700002d",
  "name" : "Sum The Strings",
  "slug" : "sum-the-strings",
  "url" : "https://www.codewars.com/kata/5966e33c4e686b508700002d",
  "category" : "reference",
  "languages" : [ "javascript", "python", "haskell", "ruby", "crystal", "coffeescript", "cpp", "swift", "csharp", "c", "cobol", "scala", "julia", "typescript", "java" ],
  "path" : "/projects/69d60c83b2c23c841dc51098/",
  "selectedLanguage" : "java",
  "description" : "Create a function that takes 2 integers in form of a string as an input, and outputs the sum (also as a string):\n\nExample: (**Input1, Input2 -->Output**)\n\n```\n\"4\",  \"5\" --> \"9\"\n\"34\", \"5\" --> \"39\"\n\"\", \"\" --> \"0\"\n\"2\", \"\" --> \"2\"\n\"-5\", \"3\" --> \"-2\"\n```\n\nNotes:\n- If either input is an empty string, consider it as zero.\n\n- Inputs and the expected output will never exceed the signed 32-bit integer limit (`2^31 - 1`)",
  "rank" : {
    "id" : -8,
    "name" : "8 kyu",
    "color" : "white"
  },
  "tags" : [ "Fundamentals" ],
  "workUrl" : "https://www.codewars.com/kata/5966e33c4e686b508700002d/train/java",
  "completed" : true
}